wcf/MyHTMLParser.py
wcf/__init__.py
wcf/datatypes.py
wcf/dictionary.py
wcf/records/__init__.py
wcf/records/attributes.py
wcf/records/base.py
wcf/records/elements.py
wcf/records/text.py
wcf/xml2records.py
wcf-0.5.5.dist-info/LICENSE.txt
wcf-0.5.5.dist-info/WHEEL
wcf-0.5.5.dist-info/METADATA
wcf-0.5.5.dist-info/RECORD
