Metadata-Version: 2.1
Name: wcf
Version: 0.5.5
Summary: A library for transforming wcf-binary data from and to xml
Home-page: https://github.com/caiyunapp/python-wcfbin
Keywords: wcf,wcf.records,tests
Author: BlueC0re
Author-email: coding@bluec0re.eu
Requires-Python: >=3.6,<4.0
Classifier: Development Status :: 4 - Beta
Classifier: License :: OSI Approved :: BSD License
Classifier: Programming Language :: Python :: 3
Classifier: Programming Language :: Python :: 3.6
Classifier: Programming Language :: Python :: 3.7
Classifier: Programming Language :: Python :: 3.8
Classifier: Topic :: Internet :: WWW/HTTP
Classifier: Topic :: Software Development :: Libraries :: Python Modules
Classifier: Topic :: Utilities
Project-URL: Repository, https://github.com/caiyunapp/python-wcfbin
